MANIFEST.in
README.rst
setup.cfg
setup.py
dagrt/__init__.py
dagrt/builtins_python.py
dagrt/data.py
dagrt/exec_numpy.py
dagrt/expression.py
dagrt/function_registry.py
dagrt/language.py
dagrt/transform.py
dagrt/utils.py
dagrt/version.py
dagrt.egg-info/PKG-INFO
dagrt.egg-info/SOURCES.txt
dagrt.egg-info/dependency_links.txt
dagrt.egg-info/requires.txt
dagrt.egg-info/top_level.txt
dagrt/codegen/__init__.py
dagrt/codegen/analysis.py
dagrt/codegen/codegen_base.py
dagrt/codegen/dag_ast.py
dagrt/codegen/expressions.py
dagrt/codegen/fortran.py
dagrt/codegen/python.py
dagrt/codegen/transform.py
dagrt/codegen/utils.py
doc/Makefile
doc/codegen.rst
doc/conf.py
doc/index.rst
doc/language.rst
doc/make.bat
doc/misc.rst
examples/adaptive_rk.py
test/conftest.py
test/test_arrays_and_linalg.f90
test/test_ast.py
test/test_builtins.py
test/test_code_builder.py
test/test_codegen.py
test/test_codegen_fortran.py
test/test_codegen_python.py
test/test_expressions.py
test/test_selfdep.f90
test/utils.py